Ruster/__init__.py
Ruster/app.py
Ruster/blueprints.py
Ruster/exceptions.py
Ruster/hasher.py
Ruster/jwt.py
Ruster/limiter.py
Ruster/mailer.py
Ruster/sanitizer.py
Ruster/session.py
Ruster/wtf.py
Ruster-2.1.0.dist-info/METADATA
Ruster-2.1.0.dist-info/WHEEL
Ruster-2.1.0.dist-info/entry_points.txt
Ruster-2.1.0.dist-info/top_level.txt
Ruster-2.1.0.dist-info/RECORD
